collector_mq_queue/main.py
collector_mq_queue/manager.py
collector_mq_queue/settings_monitor.py
collector_mq_queue/test_queue_manager.py
collector_mq_queue-0.1.1.dist-info/METADATA
collector_mq_queue-0.1.1.dist-info/WHEEL
collector_mq_queue-0.1.1.dist-info/entry_points.txt
collector_mq_queue-0.1.1.dist-info/RECORD
